compiling_loader/__init__.py
compiling_loader/ast_builder.py
compiling_loader/compiler.py
compiling_loader/compiler_state.py
compiling_loader/generator.py
compiling_loader/generator_defaulttags.py
compiling_loader/generator_flt_expr.py
compiling_loader/generator_loader_tags.py
compiling_loader/generator_smartif.py
compiling_loader/html.py
compiling_loader/loader.py
compiling_loader/util.py
django_compiling_loader-0.0.1.dist-info/DESCRIPTION.rst
django_compiling_loader-0.0.1.dist-info/METADATA
django_compiling_loader-0.0.1.dist-info/metadata.json
django_compiling_loader-0.0.1.dist-info/RECORD
django_compiling_loader-0.0.1.dist-info/top_level.txt
django_compiling_loader-0.0.1.dist-info/WHEEL
