Metadata-Version: 2.0
Name: django-compiling-loader
Version: 0.0.1
Summary: A bytecode compiling template loader for Django
Home-page: https://github.com/mhallin/django-compiling-loader
Author: Magnus Hallin
Author-email: mhallin@gmail.com
License: BSD
Keywords: django performance template
Platform: UNKNOWN
Classifier: Development Status :: 4 - Beta
Classifier: Framework :: Django
Classifier: Framework :: Django :: 1.7
Classifier: Intended Audience :: Developers
Classifier: License :: OSI Approved :: BSD License
Classifier: Programming Language :: Python :: 3
Classifier: Programming Language :: Python :: 3.4
Classifier: Topic :: Software Development :: Compilers
Provides-Extra: dist
Requires-Dist: twine; extra == 'dist'
Requires-Dist: wheel; extra == 'dist'
Provides-Extra: test
Requires-Dist: pytest (~=2.7.2); extra == 'test'
Requires-Dist: pytest-cov (~=1.8.1); extra == 'test'
Requires-Dist: pytest-django (~=2.8.0); extra == 'test'
Requires-Dist: Django (~=1.7.0); extra == 'test'
